[{"name":"pinHp0","pinType":1,"rarity":0,"index":0,"bonus":1,"craftCost":20,"id":35},{"name":"pinHp1","pinType":1,"rarity":0,"index":1,"bonus":1,"craftCost":20,"id":36},{"name":"pinHp2","pinType":1,"rarity":0,"index":2,"bonus":1,"craftCost":20,"id":37},{"name":"pinAtt0","pinType":2,"rarity":0,"index":0,"bonus":1,"craftCost":20,"id":38},{"name":"pinAtt1","pinType":2,"rarity":0,"index":1,"bonus":1,"craftCost":20,"id":39},{"name":"pinAtt2","pinType":2,"rarity":0,"index":2,"bonus":1,"craftCost":20,"id":40},{"name":"pinUlti0","pinType":3,"rarity":0,"index":0,"bonus":1,"craftCost":20,"id":41},{"name":"pinUlti1","pinType":3,"rarity":0,"index":1,"bonus":1,"craftCost":20,"id":42},{"name":"pinUlti2","pinType":3,"rarity":0,"index":2,"bonus":1,"craftCost":20,"id":43},{"name":"badgeHp0","pinType":1,"rarity":1,"index":0,"bonus":2,"craftCost":50,"id":44},{"name":"badgeHp1","pinType":1,"rarity":1,"index":1,"bonus":2,"craftCost":50,"id":45},{"name":"badgeAtt0","pinType":2,"rarity":1,"index":0,"bonus":2,"craftCost":50,"id":46},{"name":"bargeAtt1","pinType":2,"rarity":1,"index":1,"bonus":2,"craftCost":50,"id":47},{"name":"badgeUlti0","pinType":3,"rarity":1,"index":0,"bonus":2,"craftCost":50,"id":48},{"name":"badgeUlti1","pinType":3,"rarity":1,"index":1,"bonus":2,"craftCost":50,"id":49},{"name":"medalHp","pinType":1,"rarity":2,"index":0,"bonus":3,"craftCost":120,"id":50},{"name":"medalAtt","pinType":2,"rarity":2,"index":0,"bonus":3,"craftCost":120,"id":51},{"name":"medalUlti","pinType":3,"rarity":2,"index":0,"bonus":3,"craftCost":120,"id":52},{"name":"crest0","pinType":4,"rarity":3,"index":0,"bonus":4,"craftCost":300,"id":53},{"name":"crest1","pinType":4,"rarity":3,"index":1,"bonus":4,"craftCost":300,"id":54},{"name":"crest2","pinType":4,"rarity":3,"index":2,"bonus":4,"craftCost":300,"id":55},{"name":"brawlstar","pinType":5,"rarity":4,"index":0,"bonus":8,"craftCost":1000,"id":56}]