[
    {
        "name": "Campaign_tutorial_1",
        "location": "Planet1",
        "allowed_heroes": "GenericSoldier",
        "reward": "Diamonds:3:",
        "map": "Pvp1",
        "enemies": "CampaignAlienRanged",
        "enemy_level": 1,
        "base": "CampaignBase",
        "num_bases": 0,
        "base_level": 1,
        "tower": "CampaignCannon",
        "num_towers": 0,
        "tower_level": 1,
        "required_stars": 3,
        "name_en": null
    },
    {
        "name": "Campaign_tutorial_2",
        "location": "Planet1",
        "allowed_heroes": "GenericSoldier",
        "reward": "Diamonds:3:",
        "map": "Pvp2",
        "enemies": "CampaignAlienRanged",
        "enemy_level": 1,
        "base": "CampaignBase",
        "num_bases": 0,
        "base_level": 1,
        "tower": "CampaignCannon",
        "num_towers": 0,
        "tower_level": 1,
        "required_stars": 4,
        "name_en": null
    },
    {
        "name": "Campaign_tutorial_3",
        "location": "Planet1",
        "allowed_heroes": "GenericSoldier",
        "reward": "Diamonds:3:",
        "map": "Pvp3",
        "enemies": "CampaignAlienRanged",
        "enemy_level": 1,
        "base": "CampaignBase",
        "num_bases": 0,
        "base_level": 1,
        "tower": "CampaignCannon",
        "num_towers": 0,
        "tower_level": 1,
        "required_stars": 5,
        "name_en": null
    },
    {
        "name": "Campaign_1",
        "location": "Planet1",
        "allowed_heroes": "GenericSoldier",
        "reward": "Diamonds:3:",
        "map": "Defense3",
        "enemies": "CampaignAlienRanged,CampaignAlienMelee",
        "enemy_level": 4,
        "base": "CampaignBase",
        "num_bases": 1,
        "base_level": 4,
        "tower": "CampaignCannon",
        "num_towers": 2,
        "tower_level": 4,
        "required_stars": 10,
        "name_en": null
    },
    {
        "name": "Campaign_2",
        "location": "Planet1",
        "allowed_heroes": "GenericSoldier",
        "reward": "Diamonds:3:",
        "map": "Defense2",
        "enemies": "CampaignAlienRanged,CampaignAlienMelee",
        "enemy_level": 3,
        "base": "CampaignBase",
        "num_bases": 1,
        "base_level": 3,
        "tower": "CampaignCannon",
        "num_towers": 3,
        "tower_level": 3,
        "required_stars": 9,
        "name_en": null
    },
    {
        "name": "Campaign_3",
        "location": "Planet1",
        "allowed_heroes": "GenericSoldier",
        "reward": "Diamonds:3:",
        "map": "Pvp4",
        "enemies": "CampaignAlienRangedFast,CampaignAlienMeleeFast",
        "enemy_level": 5,
        "base": "CampaignBase",
        "num_bases": 0,
        "base_level": 5,
        "tower": "CampaignCannon",
        "num_towers": 0,
        "tower_level": 5,
        "required_stars": 7,
        "name_en": null
    },
    {
        "name": "Campaign_4",
        "location": "Planet2",
        "allowed_heroes": "GenericSoldier",
        "reward": "Diamonds:3:",
        "map": "Defense1",
        "enemies": "CampaignAlienRanged,CampaignAlienMelee",
        "enemy_level": 1,
        "base": "CampaignDrone",
        "num_bases": 1,
        "base_level": 1,
        "tower": "CampaignCannon",
        "num_towers": 0,
        "tower_level": 1,
        "required_stars": 6,
        "name_en": null
    },
    {
        "name": "Campaign_4_1",
        "location": "Planet2",
        "allowed_heroes": "GenericSoldier",
        "reward": "Diamonds:3:",
        "map": "Defense3",
        "enemies": "CampaignAlienRanged,CampaignAlienMelee",
        "enemy_level": 6,
        "base": "CampaignBase",
        "num_bases": 1,
        "base_level": 6,
        "tower": "CampaignCannon",
        "num_towers": 2,
        "tower_level": 6,
        "required_stars": 12,
        "name_en": null
    },
    {
        "name": "Campaign_5",
        "location": "Planet2",
        "allowed_heroes": "GenericSoldier",
        "reward": "Diamonds:3:",
        "map": "Defense2",
        "enemies": "CampaignAlienRanged,CampaignAlienMelee",
        "enemy_level": 6,
        "base": "CampaignBase",
        "num_bases": 1,
        "base_level": 6,
        "tower": "CampaignCannon",
        "num_towers": 3,
        "tower_level": 6,
        "required_stars": 12,
        "name_en": null
    },
    {
        "name": "Campaign_6",
        "location": "Planet2",
        "allowed_heroes": "GenericSoldier",
        "reward": "Diamonds:3:",
        "map": "Pvp5",
        "enemies": "CampaignAlienRangedFast,CampaignAlienMeleeFast",
        "enemy_level": 8,
        "base": "CampaignBase",
        "num_bases": 0,
        "base_level": 8,
        "tower": "CampaignCannon",
        "num_towers": 0,
        "tower_level": 8,
        "required_stars": 10,
        "name_en": null
    },
    {
        "name": "Campaign_7",
        "location": "Planet2",
        "allowed_heroes": "GenericSoldier",
        "reward": "Diamonds:3:",
        "map": "Defense1",
        "enemies": "CampaignAlienRanged,CampaignAlienMelee",
        "enemy_level": 3,
        "base": "CampaignDrone",
        "num_bases": 1,
        "base_level": 3,
        "tower": "CampaignCannon",
        "num_towers": 0,
        "tower_level": 3,
        "required_stars": 9,
        "name_en": null
    },
    {
        "name": "Campaign_8",
        "location": "Planet2",
        "allowed_heroes": "GenericSoldier",
        "reward": "Diamonds:3:",
        "map": "Defense3",
        "enemies": "CampaignAlienRanged,CampaignAlienMelee",
        "enemy_level": 8,
        "base": "CampaignBase",
        "num_bases": 1,
        "base_level": 8,
        "tower": "CampaignCannon",
        "num_towers": 2,
        "tower_level": 8,
        "required_stars": 14,
        "name_en": null
    },
    {
        "name": "Campaign_9",
        "location": "Planet3",
        "allowed_heroes": "GenericSoldier",
        "reward": "Diamonds:3:",
        "map": "Defense2",
        "enemies": "CampaignAlienRanged,CampaignAlienMelee",
        "enemy_level": 8,
        "base": "CampaignBase",
        "num_bases": 1,
        "base_level": 8,
        "tower": "CampaignCannon",
        "num_towers": 3,
        "tower_level": 8,
        "required_stars": 14,
        "name_en": null
    },
    {
        "name": "Campaign_10",
        "location": "Planet3",
        "allowed_heroes": "GenericSoldier",
        "reward": "Diamonds:3:",
        "map": "Pvp6",
        "enemies": "CampaignAlienRangedFast,CampaignAlienMeleeFast",
        "enemy_level": 9,
        "base": "CampaignBase",
        "num_bases": 0,
        "base_level": 9,
        "tower": "CampaignCannon",
        "num_towers": 0,
        "tower_level": 9,
        "required_stars": 11,
        "name_en": null
    },
    {
        "name": "Campaign_11",
        "location": "Planet3",
        "allowed_heroes": "GenericSoldier",
        "reward": "Diamonds:3:",
        "map": "Defense1",
        "enemies": "CampaignAlienRanged,CampaignAlienMelee",
        "enemy_level": 4,
        "base": "CampaignDrone",
        "num_bases": 1,
        "base_level": 4,
        "tower": "CampaignCannon",
        "num_towers": 0,
        "tower_level": 4,
        "required_stars": 10,
        "name_en": null
    },
    {
        "name": "Campaign_12",
        "location": "Planet3",
        "allowed_heroes": "GenericSoldier",
        "reward": "Diamonds:3:",
        "map": "Defense3",
        "enemies": "CampaignAlienRanged,CampaignAlienMelee",
        "enemy_level": 10,
        "base": "CampaignBase",
        "num_bases": 1,
        "base_level": 10,
        "tower": "CampaignCannon",
        "num_towers": 2,
        "tower_level": 10,
        "required_stars": 16,
        "name_en": null
    },
    {
        "name": "Campaign_13",
        "location": "Planet3",
        "allowed_heroes": "GenericSoldier",
        "reward": "Diamonds:3:",
        "map": "Defense2",
        "enemies": "CampaignAlienRanged,CampaignAlienMelee",
        "enemy_level": 9,
        "base": "CampaignBase",
        "num_bases": 1,
        "base_level": 9,
        "tower": "CampaignCannon",
        "num_towers": 3,
        "tower_level": 9,
        "required_stars": 15,
        "name_en": null
    },
    {
        "name": "Campaign_14",
        "location": "Planet3",
        "allowed_heroes": "GenericSoldier",
        "reward": "Diamonds:3:",
        "map": "Pvp7",
        "enemies": "CampaignAlienRangedFast,CampaignAlienMeleeFast",
        "enemy_level": 10,
        "base": "CampaignBase",
        "num_bases": 0,
        "base_level": 10,
        "tower": "CampaignCannon",
        "num_towers": 0,
        "tower_level": 10,
        "required_stars": 12,
        "name_en": null
    },
    {
        "name": "Campaign_15",
        "location": "Planet4",
        "allowed_heroes": "GenericSoldier",
        "reward": "Diamonds:3:",
        "map": "Defense1",
        "enemies": "CampaignAlienRanged,CampaignAlienMelee",
        "enemy_level": 6,
        "base": "CampaignDrone",
        "num_bases": 1,
        "base_level": 6,
        "tower": "CampaignCannon",
        "num_towers": 0,
        "tower_level": 6,
        "required_stars": 12,
        "name_en": null
    },
    {
        "name": "Campaign_16",
        "location": "Planet4",
        "allowed_heroes": "GenericSoldier",
        "reward": "Diamonds:3:",
        "map": "Defense3",
        "enemies": "CampaignAlienRanged,CampaignAlienMelee",
        "enemy_level": 11,
        "base": "CampaignBase",
        "num_bases": 1,
        "base_level": 11,
        "tower": "CampaignCannon",
        "num_towers": 2,
        "tower_level": 11,
        "required_stars": 17,
        "name_en": null
    },
    {
        "name": "Campaign_17",
        "location": "Planet4",
        "allowed_heroes": "GenericSoldier",
        "reward": "Diamonds:3:",
        "map": "Defense2",
        "enemies": "CampaignAlienRanged,CampaignAlienMelee",
        "enemy_level": 10,
        "base": "CampaignBase",
        "num_bases": 1,
        "base_level": 10,
        "tower": "CampaignCannon",
        "num_towers": 3,
        "tower_level": 10,
        "required_stars": 16,
        "name_en": null
    },
    {
        "name": "Campaign_18",
        "location": "Planet4",
        "allowed_heroes": "GenericSoldier",
        "reward": "Diamonds:3:",
        "map": "Pvp8",
        "enemies": "CampaignAlienRangedFast,CampaignAlienMeleeFast",
        "enemy_level": 12,
        "base": "CampaignBase",
        "num_bases": 0,
        "base_level": 12,
        "tower": "CampaignCannon",
        "num_towers": 0,
        "tower_level": 12,
        "required_stars": 14,
        "name_en": null
    },
    {
        "name": "Campaign_19",
        "location": "Planet4",
        "allowed_heroes": "GenericSoldier",
        "reward": "Diamonds:3:",
        "map": "Defense1",
        "enemies": "CampaignAlienRanged,CampaignAlienMelee",
        "enemy_level": 6,
        "base": "CampaignDrone",
        "num_bases": 1,
        "base_level": 6,
        "tower": "CampaignCannon",
        "num_towers": 0,
        "tower_level": 6,
        "required_stars": 12,
        "name_en": null
    },
    {
        "name": "Campaign_20",
        "location": "Planet4",
        "allowed_heroes": "GenericSoldier",
        "reward": "Diamonds:3:",
        "map": "Defense3",
        "enemies": "CampaignAlienRanged,CampaignAlienMelee",
        "enemy_level": 12,
        "base": "CampaignBase",
        "num_bases": 1,
        "base_level": 12,
        "tower": "CampaignCannon",
        "num_towers": 2,
        "tower_level": 12,
        "required_stars": 18,
        "name_en": null
    },
    {
        "name": "Campaign_21",
        "location": "Planet5",
        "allowed_heroes": "GenericSoldier",
        "reward": "Diamonds:3:",
        "map": "Defense2",
        "enemies": "CampaignAlienRanged,CampaignAlienMelee",
        "enemy_level": 11,
        "base": "CampaignBase",
        "num_bases": 1,
        "base_level": 11,
        "tower": "CampaignCannon",
        "num_towers": 3,
        "tower_level": 11,
        "required_stars": 17,
        "name_en": null
    },
    {
        "name": "Campaign_22",
        "location": "Planet5",
        "allowed_heroes": "GenericSoldier",
        "reward": "Diamonds:3:",
        "map": "Pvp9",
        "enemies": "CampaignAlienRangedFast,CampaignAlienMeleeFast",
        "enemy_level": 12,
        "base": "CampaignBase",
        "num_bases": 0,
        "base_level": 12,
        "tower": "CampaignCannon",
        "num_towers": 0,
        "tower_level": 12,
        "required_stars": 14,
        "name_en": null
    },
    {
        "name": "Campaign_23",
        "location": "Planet5",
        "allowed_heroes": "GenericSoldier",
        "reward": "Diamonds:3:",
        "map": "Defense1",
        "enemies": "CampaignAlienRanged,CampaignAlienMelee",
        "enemy_level": 8,
        "base": "CampaignDrone",
        "num_bases": 1,
        "base_level": 8,
        "tower": "CampaignCannon",
        "num_towers": 0,
        "tower_level": 8,
        "required_stars": 14,
        "name_en": null
    },
    {
        "name": "Campaign_24",
        "location": "Planet5",
        "allowed_heroes": "GenericSoldier",
        "reward": "Diamonds:3:",
        "map": "Defense3",
        "enemies": "CampaignAlienRanged,CampaignAlienMelee",
        "enemy_level": 13,
        "base": "CampaignBase",
        "num_bases": 1,
        "base_level": 13,
        "tower": "CampaignCannon",
        "num_towers": 2,
        "tower_level": 13,
        "required_stars": 19,
        "name_en": null
    },
    {
        "name": "Campaign_25",
        "location": "Planet5",
        "allowed_heroes": "GenericSoldier",
        "reward": "Diamonds:3:",
        "map": "Defense2",
        "enemies": "CampaignAlienRanged,CampaignAlienMelee",
        "enemy_level": 12,
        "base": "CampaignBase",
        "num_bases": 1,
        "base_level": 12,
        "tower": "CampaignCannon",
        "num_towers": 3,
        "tower_level": 12,
        "required_stars": 18,
        "name_en": null
    },
    {
        "name": "Campaign_26",
        "location": "Planet5",
        "allowed_heroes": "GenericSoldier",
        "reward": "Diamonds:3:",
        "map": "Pvp10",
        "enemies": "CampaignAlienRangedFast,CampaignAlienMeleeFast",
        "enemy_level": 14,
        "base": "CampaignBase",
        "num_bases": 0,
        "base_level": 14,
        "tower": "CampaignCannon",
        "num_towers": 0,
        "tower_level": 14,
        "required_stars": 16,
        "name_en": null
    },
    {
        "name": "Campaign_27",
        "location": "Planet6",
        "allowed_heroes": "GenericSoldier",
        "reward": "Diamonds:3:",
        "map": "Defense1",
        "enemies": "CampaignAlienRanged,CampaignAlienMelee",
        "enemy_level": 8,
        "base": "CampaignDrone",
        "num_bases": 1,
        "base_level": 8,
        "tower": "CampaignCannon",
        "num_towers": 0,
        "tower_level": 8,
        "required_stars": 14,
        "name_en": null
    },
    {
        "name": "Campaign_28",
        "location": "Planet6",
        "allowed_heroes": "GenericSoldier",
        "reward": "Diamonds:3:",
        "map": "Defense3",
        "enemies": "CampaignAlienRanged,CampaignAlienMelee",
        "enemy_level": 14,
        "base": "CampaignBase",
        "num_bases": 1,
        "base_level": 14,
        "tower": "CampaignCannon",
        "num_towers": 2,
        "tower_level": 14,
        "required_stars": 20,
        "name_en": null
    },
    {
        "name": "Campaign_29",
        "location": "Planet6",
        "allowed_heroes": "GenericSoldier",
        "reward": "Diamonds:3:",
        "map": "Defense2",
        "enemies": "CampaignAlienRanged,CampaignAlienMelee",
        "enemy_level": 13,
        "base": "CampaignBase",
        "num_bases": 1,
        "base_level": 13,
        "tower": "CampaignCannon",
        "num_towers": 3,
        "tower_level": 13,
        "required_stars": 19,
        "name_en": null
    },
    {
        "name": "Campaign_30",
        "location": "Planet6",
        "allowed_heroes": "GenericSoldier",
        "reward": "Diamonds:3:",
        "map": "Pvp1",
        "enemies": "CampaignAlienRangedFast,CampaignAlienMeleeFast",
        "enemy_level": 14,
        "base": "CampaignBase",
        "num_bases": 0,
        "base_level": 14,
        "tower": "CampaignCannon",
        "num_towers": 0,
        "tower_level": 14,
        "required_stars": 16,
        "name_en": null
    },
    {
        "name": "Campaign_31",
        "location": "Planet6",
        "allowed_heroes": "GenericSoldier",
        "reward": "Diamonds:3:",
        "map": "Defense1",
        "enemies": "CampaignAlienRanged,CampaignAlienMelee",
        "enemy_level": 9,
        "base": "CampaignDrone",
        "num_bases": 1,
        "base_level": 9,
        "tower": "CampaignCannon",
        "num_towers": 0,
        "tower_level": 9,
        "required_stars": 15,
        "name_en": null
    },
    {
        "name": "Campaign_32",
        "location": "Planet6",
        "allowed_heroes": "GenericSoldier",
        "reward": "Diamonds:3:",
        "map": "Defense3",
        "enemies": "CampaignAlienRanged,CampaignAlienMelee",
        "enemy_level": 15,
        "base": "CampaignBase",
        "num_bases": 1,
        "base_level": 15,
        "tower": "CampaignCannon",
        "num_towers": 2,
        "tower_level": 15,
        "required_stars": 21,
        "name_en": null
    },
    {
        "name": "Campaign_33",
        "location": "Planet7",
        "allowed_heroes": "GenericSoldier",
        "reward": "Diamonds:3:",
        "map": "Defense2",
        "enemies": "CampaignAlienRanged,CampaignAlienMelee",
        "enemy_level": 14,
        "base": "CampaignBase",
        "num_bases": 1,
        "base_level": 14,
        "tower": "CampaignCannon",
        "num_towers": 3,
        "tower_level": 14,
        "required_stars": 20,
        "name_en": null
    },
    {
        "name": "Campaign_34",
        "location": "Planet7",
        "allowed_heroes": "GenericSoldier",
        "reward": "Diamonds:3:",
        "map": "Pvp2",
        "enemies": "CampaignAlienRangedFast,CampaignAlienMeleeFast",
        "enemy_level": 15,
        "base": "CampaignBase",
        "num_bases": 0,
        "base_level": 15,
        "tower": "CampaignCannon",
        "num_towers": 0,
        "tower_level": 15,
        "required_stars": 17,
        "name_en": null
    },
    {
        "name": "Campaign_35",
        "location": "Planet7",
        "allowed_heroes": "GenericSoldier",
        "reward": "Diamonds:3:",
        "map": "Defense1",
        "enemies": "CampaignAlienRanged,CampaignAlienMelee",
        "enemy_level": 10,
        "base": "CampaignDrone",
        "num_bases": 1,
        "base_level": 10,
        "tower": "CampaignCannon",
        "num_towers": 0,
        "tower_level": 10,
        "required_stars": 16,
        "name_en": null
    },
    {
        "name": "Campaign_36",
        "location": "Planet7",
        "allowed_heroes": "GenericSoldier",
        "reward": "Diamonds:3:",
        "map": "Defense3",
        "enemies": "CampaignAlienRanged,CampaignAlienMelee",
        "enemy_level": 16,
        "base": "CampaignBase",
        "num_bases": 1,
        "base_level": 16,
        "tower": "CampaignCannon",
        "num_towers": 2,
        "tower_level": 16,
        "required_stars": 22,
        "name_en": null
    },
    {
        "name": "Campaign_37",
        "location": "Planet7",
        "allowed_heroes": "GenericSoldier",
        "reward": "Diamonds:3:",
        "map": "Defense2",
        "enemies": "CampaignAlienRanged,CampaignAlienMelee",
        "enemy_level": 14,
        "base": "CampaignBase",
        "num_bases": 1,
        "base_level": 14,
        "tower": "CampaignCannon",
        "num_towers": 3,
        "tower_level": 14,
        "required_stars": 20,
        "name_en": null
    },
    {
        "name": "Campaign_38",
        "location": "Planet7",
        "allowed_heroes": "GenericSoldier",
        "reward": "Diamonds:3:",
        "map": "Pvp3",
        "enemies": "CampaignAlienRangedFast,CampaignAlienMeleeFast",
        "enemy_level": 16,
        "base": "CampaignBase",
        "num_bases": 0,
        "base_level": 16,
        "tower": "CampaignCannon",
        "num_towers": 0,
        "tower_level": 16,
        "required_stars": 18,
        "name_en": null
    },
    {
        "name": "Campaign_39",
        "location": "Planet7",
        "allowed_heroes": "GenericSoldier",
        "reward": "Diamonds:3:",
        "map": "Defense1",
        "enemies": "CampaignAlienRanged,CampaignAlienMelee",
        "enemy_level": 11,
        "base": "CampaignDrone",
        "num_bases": 1,
        "base_level": 11,
        "tower": "CampaignCannon",
        "num_towers": 0,
        "tower_level": 11,
        "required_stars": 17,
        "name_en": null
    },
    {
        "name": "Campaign_40",
        "location": "Planet7",
        "allowed_heroes": "GenericSoldier",
        "reward": "Diamonds:3:",
        "map": "Defense1",
        "enemies": "CampaignAlienRanged,CampaignAlienMelee",
        "enemy_level": 15,
        "base": "CampaignBase",
        "num_bases": 1,
        "base_level": 15,
        "tower": "CampaignCannon",
        "num_towers": 4,
        "tower_level": 15,
        "required_stars": 21,
        "name_en": null
    },
    {
        "name": "Campaign_41",
        "location": "Planet7",
        "allowed_heroes": "GenericSoldier",
        "reward": "Diamonds:3:",
        "map": "Defense1",
        "enemies": "CampaignAlienRanged,CampaignAlienMelee",
        "enemy_level": 16,
        "base": "CampaignBase",
        "num_bases": 1,
        "base_level": 15,
        "tower": "CampaignCannon",
        "num_towers": 4,
        "tower_level": 15,
        "required_stars": 22,
        "name_en": null
    },
    {
        "name": "Campaign_42",
        "location": "Planet7",
        "allowed_heroes": "GenericSoldier",
        "reward": "Diamonds:3:",
        "map": "Defense1",
        "enemies": "CampaignAlienRanged,CampaignAlienMelee",
        "enemy_level": 17,
        "base": "CampaignBase",
        "num_bases": 1,
        "base_level": 15,
        "tower": "CampaignCannon",
        "num_towers": 4,
        "tower_level": 15,
        "required_stars": 23,
        "name_en": null
    },
    {
        "name": "Campaign_43",
        "location": "Planet7",
        "allowed_heroes": "GenericSoldier",
        "reward": "Diamonds:3:",
        "map": "Defense1",
        "enemies": "CampaignAlienRanged,CampaignAlienMelee",
        "enemy_level": 18,
        "base": "CampaignBase",
        "num_bases": 1,
        "base_level": 15,
        "tower": "CampaignCannon",
        "num_towers": 4,
        "tower_level": 15,
        "required_stars": 24,
        "name_en": null
    },
    {
        "name": "Campaign_44",
        "location": "Planet7",
        "allowed_heroes": "GenericSoldier",
        "reward": "Diamonds:3:",
        "map": "Defense1",
        "enemies": "CampaignAlienRanged,CampaignAlienMelee",
        "enemy_level": 19,
        "base": "CampaignBase",
        "num_bases": 1,
        "base_level": 15,
        "tower": "CampaignCannon",
        "num_towers": 4,
        "tower_level": 15,
        "required_stars": 25,
        "name_en": null
    },
    {
        "name": "Campaign_45",
        "location": "Planet7",
        "allowed_heroes": "GenericSoldier",
        "reward": "Diamonds:3:",
        "map": "Defense1",
        "enemies": "CampaignAlienRanged,CampaignAlienMelee",
        "enemy_level": 20,
        "base": "CampaignBase",
        "num_bases": 1,
        "base_level": 15,
        "tower": "CampaignCannon",
        "num_towers": 4,
        "tower_level": 15,
        "required_stars": 26,
        "name_en": null
    },
    {
        "name": "Campaign_46",
        "location": "Planet7",
        "allowed_heroes": "GenericSoldier",
        "reward": "Diamonds:3:",
        "map": "Defense1",
        "enemies": "CampaignAlienRanged,CampaignAlienMelee",
        "enemy_level": 20,
        "base": "CampaignBase",
        "num_bases": 1,
        "base_level": 15,
        "tower": "CampaignCannon",
        "num_towers": 4,
        "tower_level": 15,
        "required_stars": 27,
        "name_en": null
    },
    {
        "name": "Campaign_47",
        "location": "Planet7",
        "allowed_heroes": "GenericSoldier",
        "reward": "Diamonds:3:",
        "map": "Defense1",
        "enemies": "CampaignAlienRanged,CampaignAlienMelee",
        "enemy_level": 20,
        "base": "CampaignBase",
        "num_bases": 1,
        "base_level": 15,
        "tower": "CampaignCannon",
        "num_towers": 4,
        "tower_level": 15,
        "required_stars": 27,
        "name_en": null
    },
    {
        "name": "Campaign_48",
        "location": "Planet7",
        "allowed_heroes": "GenericSoldier",
        "reward": "Diamonds:3:",
        "map": "Defense1",
        "enemies": "CampaignAlienRanged,CampaignAlienMelee",
        "enemy_level": 20,
        "base": "CampaignBase",
        "num_bases": 1,
        "base_level": 15,
        "tower": "CampaignCannon",
        "num_towers": 4,
        "tower_level": 15,
        "required_stars": 27,
        "name_en": null
    },
    {
        "name": "Campaign_49",
        "location": "Planet7",
        "allowed_heroes": "GenericSoldier",
        "reward": "Diamonds:3:",
        "map": "Defense1",
        "enemies": "CampaignAlienRanged,CampaignAlienMelee",
        "enemy_level": 20,
        "base": "CampaignBase",
        "num_bases": 1,
        "base_level": 15,
        "tower": "CampaignCannon",
        "num_towers": 4,
        "tower_level": 15,
        "required_stars": 27,
        "name_en": null
    },
    {
        "name": "Campaign_50",
        "location": "Planet7",
        "allowed_heroes": "GenericSoldier",
        "reward": "Diamonds:3:",
        "map": "Defense1",
        "enemies": "CampaignAlienRanged,CampaignAlienMelee",
        "enemy_level": 20,
        "base": "CampaignBase",
        "num_bases": 1,
        "base_level": 15,
        "tower": "CampaignCannon",
        "num_towers": 4,
        "tower_level": 15,
        "required_stars": 27,
        "name_en": null
    }
]